MANIFEST.in
README.md
requirements.txt
setup.cfg
setup.py
djfabric/__init__.py
djfabric/fab.py
djfabric.egg-info/PKG-INFO
djfabric.egg-info/SOURCES.txt
djfabric.egg-info/dependency_links.txt
djfabric.egg-info/requires.txt
djfabric.egg-info/top_level.txt