Metadata-Version: 2.1
Name: djfabric
Version: 0.0.9
Summary: Django deploy app
Home-page: https://github.com/pmaigutyak/djfabric
Download-URL: https://github.com/pmaigutyak/djfabric/archive/0.0.9.tar.gz
Author: Paul Maigutyak
Author-email: pmaigutyak@gmail.com
License: MIT
